LICENSE
README.md
setup.cfg
setup.py
eiq_logging/__init__.py
eiq_logging/constants.py
eiq_logging/gunicorn.py
eiq_logging/handlers.py
eiq_logging/helpers.py
eiq_logging/renderers.py
eiq_logging.egg-info/PKG-INFO
eiq_logging.egg-info/SOURCES.txt
eiq_logging.egg-info/dependency_links.txt
eiq_logging.egg-info/requires.txt
eiq_logging.egg-info/top_level.txt