Metadata-Version: 2.1
Name: eiq-logging
Version: 1.4
Summary: Consistent logging for EIQ projects.
Home-page: https://github.com/eclecticiq/eiq-logging-python
Author: EclecticIQ
Author-email: opensource@eclecticiq.com
License: BSD-3-Clause
Platform: UNKNOWN
Classifier: License :: OSI Approved :: BSD License
